cubicweb_elasticsearch/__init__.py
cubicweb_elasticsearch/__pkginfo__.py
cubicweb_elasticsearch/ccplugin.py
cubicweb_elasticsearch/entities.py
cubicweb_elasticsearch/es.py
cubicweb_elasticsearch/hooks.py
cubicweb_elasticsearch/schema.py
cubicweb_elasticsearch/search_helpers.py
cubicweb_elasticsearch/site_cubicweb.py
cubicweb_elasticsearch/testutils.py
cubicweb_elasticsearch/views.py
cubicweb_elasticsearch/i18n/en.po
cubicweb_elasticsearch/i18n/es.po
cubicweb_elasticsearch/i18n/fr.po
cubicweb_elasticsearch/migration/postcreate.py
cubicweb_elasticsearch/pviews/__init__.py
cubicweb_elasticsearch/pviews/espanel.py
cubicweb_elasticsearch/pviews/templates/espanel.jinja2
cubicweb_elasticsearch-2.0.0.dist-info/METADATA
cubicweb_elasticsearch-2.0.0.dist-info/WHEEL
cubicweb_elasticsearch-2.0.0.dist-info/entry_points.txt
cubicweb_elasticsearch-2.0.0.dist-info/top_level.txt
cubicweb_elasticsearch-2.0.0.dist-info/RECORD
