Metadata-Version: 2.1
Name: cubicweb-elasticsearch
Version: 2.0.0
Summary: Simple ElasticSearch indexing integration for CubicWeb
Home-page: https://forge.extranet.logilab.fr/cubicweb/cubes/cubicweb-elasticsearch
Author: LOGILAB S.A. (Paris, FRANCE)
Author-email: contact@logilab.fr
License: LGPL
Classifier: Environment :: Web Environment
Classifier: Framework :: CubicWeb
Classifier: Programming Language :: Python
Classifier: Programming Language :: JavaScript
Requires-Dist: cubicweb <5.0.0,>=4.0.0
Requires-Dist: cubicweb-web <2.0.0,>=1.0.0
Requires-Dist: cwtags
Requires-Dist: elasticsearch <9.0.0,>=8.0.0
Requires-Dist: elasticsearch-dsl <9.0.0,>=8.0.0
Requires-Dist: beautifulsoup4
